MANIFEST.in
README.md
setup.py
security_engine/__init__.py
security_engine/engine.py
security_engine/handlers/__init__.py
security_engine/handlers/log/__init__.py
security_engine/handlers/log/log_handler.py
security_engine/handlers/rule/__init__.py
security_engine/handlers/rule/rule_load_handler.py
security_engine/managers/__init__.py
security_engine/managers/context.py
security_engine/managers/log.py
security_engine/managers/rule.py
security_engine/models/__init__.py
security_engine/models/action.py
security_engine/models/address.py
security_engine/models/chain.py
security_engine/models/contract.py
security_engine/models/data_source.py
security_engine/models/nft.py
security_engine/models/protocol.py
security_engine/models/rule.py
security_engine/models/sign_scene.py
security_engine/models/token.py
security_engine/models/transaction.py
security_engine/models/typed_data.py
security_engine/runtime/__init__.py
security_engine/runtime/context.py
security_engine/utils/__init__.py
security_engine/utils/format.py
security_engine/utils/register.py
security_engine/utils/validate.py
web3_security_engine.egg-info/PKG-INFO
web3_security_engine.egg-info/SOURCES.txt
web3_security_engine.egg-info/dependency_links.txt
web3_security_engine.egg-info/requires.txt
web3_security_engine.egg-info/top_level.txt